csvObject/__init__.py
csvObject/csvObject.py
csvObject/csvWriter.py
csvObject-0.8.1.dist-info/LICENSE
csvObject-0.8.1.dist-info/METADATA
csvObject-0.8.1.dist-info/WHEEL
csvObject-0.8.1.dist-info/top_level.txt
csvObject-0.8.1.dist-info/RECORD
