Metadata-Version: 2.1
Name: csvObject
Version: 0.8.1
Summary: Simple Objected based approach to using data from a csv
Home-page: UNKNOWN
Author: Samuel Baker
Author-email: samuelbaker.researcher@gmail.com
Maintainer: Samuel Baker
Maintainer-email: samuelbaker.researcher@gmail.com
License: MIT
Download-URL: https://github.com/sbaker-dev/csvObject
Platform: UNKNOWN
Classifier: Programming Language :: Python :: 3.7
Classifier: Programming Language :: Python :: 3.8
Classifier: License :: OSI Approved :: MIT License
Requires-Python: >=3.6
